ju/__init__.py
ju/json_schema.py
ju/oas.py
ju/pydantic_util.py
ju/rjsf.py
ju/traitlets_util.py
ju/util.py
ju/viz.py
ju/tests/__init__.py
ju/tests/oas_test.py
ju/tests/pydantic_util_test.py
ju/tests/rjsf_test.py
ju/tests/traitlets_util_test.py
ju-0.1.31.dist-info/LICENSE
ju-0.1.31.dist-info/METADATA
ju-0.1.31.dist-info/WHEEL
ju-0.1.31.dist-info/top_level.txt
ju-0.1.31.dist-info/RECORD
