Metadata-Version: 2.1
Name: ju
Version: 0.1.31
Summary: JSON schema Utils
License: apache-2.0
License-File: LICENSE
Requires-Dist: importlib-resources
Requires-Dist: i2
Requires-Dist: dol
Requires-Dist: pydantic
Requires-Dist: glom
Requires-Dist: datamodel-code-generator
Requires-Dist: traitlets
Requires-Dist: ipywidgets
Requires-Dist: requests
Provides-Extra: test
Requires-Dist: pytest; extra == "test"
